<?xml version="1.0" encoding="UTF-8"?>
<EIM_left_arm_2cm_18>
    <D2021-05-08_T13-53-13>
        <datetime>2021-05-08T13:53:13</datetime>
        <serialnumber></serialnumber>
        <TS>49993</TS>
        <frequency>
            <f0>976.563</f0>
            <f1>1953.13</f1>
            <f2>3906.25</f2>
            <f3>7812.5</f3>
            <f4>15625</f4>
            <f5>31250</f5>
            <f6>62500</f6>
            <f7>125000</f7>
            <f8>250000</f8>
            <f9>500000</f9>
            <f10>1e+06</f10>
        </frequency>
        <amplitude>
            <a0>70.7254</a0>
            <a1>68.8847</a1>
            <a2>73.4839</a2>
            <a3>70.3935</a3>
            <a4>67.8693</a4>
            <a5>65.6634</a5>
            <a6>64.4207</a6>
            <a7>57.6084</a7>
            <a8>51.3856</a8>
            <a9>44.3281</a9>
            <a10>39.5007</a10>
        </amplitude>
        <phase>
            <p0>-3.04602</p0>
            <p1>-2.69371</p1>
            <p2>2.3458</p2>
            <p3>1.91485</p3>
            <p4>3.31903</p4>
            <p5>5.69627</p5>
            <p6>8.32857</p6>
            <p7>11.0728</p7>
            <p8>13.5317</p8>
            <p9>13.4621</p9>
            <p10>10.7137</p10>
        </phase>
        <amplitude_rms>
            <ar0>5.566</ar0>
            <ar1>4.066</ar1>
            <ar2>2.058</ar2>
            <ar3>2.724</ar3>
            <ar4>1.023</ar4>
            <ar5>3.686</ar5>
            <ar6>2.508</ar6>
            <ar7>2.295</ar7>
            <ar8>1.978</ar8>
            <ar9>3.252</ar9>
            <ar10>3.423</ar10>
        </amplitude_rms>
        <phase_rms>
            <pr0>2.134</pr0>
            <pr1>1.658</pr1>
            <pr2>1.555</pr2>
            <pr3>1.033</pr3>
            <pr4>1.048</pr4>
            <pr5>2.429</pr5>
            <pr6>1.251</pr6>
            <pr7>1.442</pr7>
            <pr8>1.873</pr8>
            <pr9>0.9242</pr9>
            <pr10>2.149</pr10>
        </phase_rms>
        <additional1></additional1>
        <additional2></additional2>
    </D2021-05-08_T13-53-13>
</EIM_left_arm_2cm_18>
